Multiplexer/mux41.v
module mux4 (
    input wire [0:3] i,
    input wire j1, j0,
    output wire o
);
    assign o = (j1 == 0 && j0 == 0) ? i[0] :
               (j1 == 0 && j0 == 1) ? i[1] :
               (j1 == 1 && j0 == 0) ? i[2] :
                                      i[3];
endmodule

Multiplexer/mux41_tb.v
module TB;
    reg [0:3]ii;
    reg s0;reg s1;
    wire yy;
    mux4 dut(.i(ii), .j0(s0),.j1(s1),.o(yy));
    initial begin
        ii = 4'b0000;s0=1'b0;s1=1'b0;
        #5      ii = 4'b1000;s0=1'b0;s1=1'b0;
        #5      ii = 4'b0000;s0=1'b0;s1=1'b1;
        #5      ii = 4'b0100;s0=1'b0;s1=1'b1;
        #5      ii = 4'b0000;s0=1'b1;s1=1'b0;
        #5      ii = 4'b0010;s0=1'b1;s1=1'b0;
        #5      ii = 4'b0000;s0=1'b1;s1=1'b1;
        #5      ii = 4'b0001;s0=1'b1;s1=1'b1;
    end
    initial begin
        $monitor("Time = %0t: ii = %b, s0 = %b, s1 = %b, yy = %b", $time, ii, s0, s1, yy);
    end
    initial begin
        $dumpfile("mux41.vcd");
        $dumpvars(0, TB);
    end
endmodule

Multiplexer/mux41.vcd
$date
	Mon Aug 25 14:29:21 2025
$end
$version
	Icarus Verilog
$end
$timescale
	1s
$end
$scope module TB $end
$var wire 1 ! yy $end
$var reg 4 " ii [0:3] $end
$var reg 1 # s0 $end
$var reg 1 $ s1 $end
$scope module newMUX $end
$var wire 4 % i [0:3] $end
$var wire 1 & j0 $end
$var wire 1 ' j1 $end
$var wire 1 ! o $end
$upscope $end
$upscope $end
$enddefinitions $end
#0
$dumpvars
0'
0&
b0 %
0$
0#
b0 "
0!
$end
#5
1!
b1000 "
b1000 %
#10
0!
1$
1'
b0 "
b0 %
#15
b100 "
b100 %
#20
0$
0'
1#
1&
b0 "
b0 %
#25
b10 "
b10 %
#30
1$
1'
b0 "
b0 %
#35
1!
b1 "
b1 %
